ceonstock_s3/README.md
ceonstock_s3/__init__.py
ceonstock_s3/_s3_manager.py
ceonstock_s3/_submission.py
ceonstock_s3/buckets.py
ceonstock_s3/core/__init__.py
ceonstock_s3/core/base.py
ceonstock_s3/core/copy.py
ceonstock_s3/core/delete.py
ceonstock_s3/core/download.py
ceonstock_s3/core/inspect.py
ceonstock_s3/core/json_s3.py
ceonstock_s3/core/presigned.py
ceonstock_s3/core/upload.py
ceonstock_s3/errors.py
ceonstock_s3/job.py
ceonstock_s3/log/__init__.py
ceonstock_s3/log/_log.py
ceonstock_s3/log/diagnostics.py
ceonstock_s3/log/formats.py
ceonstock_s3/log/formatters.py
ceonstock_s3/log/handlers.py
ceonstock_s3/log/loggers.py
ceonstock_s3/log/logging_info.py
ceonstock_s3/log/logging_setup.py
ceonstock_s3/log/pretty_printer.py
ceonstock_s3/project.py
ceonstock_s3/public.py
ceonstock_s3/submission.py
ceonstock_s3-0.1.1.dist-info/METADATA
ceonstock_s3-0.1.1.dist-info/WHEEL
ceonstock_s3-0.1.1.dist-info/RECORD
